Metadata-Version: 1.0
Name: palavreado
Version: 0.2.0
Summary: dead simple keyword based intent parser
Home-page: https://github.com/OpenJarbas/palavreado
Author: jarbasai
Author-email: jarbasai@mailfence.com
License: apache-2.0
Platform: UNKNOWN
